{"type":"Sprite","props":{"x":0,"y":0,"presetID":1,"isPresetRoot":true},"compId":54,"child":[{"type":"Image","props":{"y":149,"x":44,"width":662,"skin":"gameimg/bg2.png","height":200,"presetID":2,"sizeGrid":"20,20,20,20"},"compId":6,"child":[{"type":"Label","props":{"y":34,"x":31,"width":609,"text":"昵称：","styleSkin":"comp/label.png","height":42,"fontSize":36,"font":"Microsoft YaHei","color":"#e59d61","align":"left","presetID":3},"compId":11},{"type":"Label","props":{"y":108,"x":30,"wordWrap":true,"width":609,"var":"nick_txt","text":"-","styleSkin":"comp/label.png","height":46,"fontSize":28,"font":"Microsoft YaHei","color":"#f8e2d0","presetID":4},"compId":12}]},{"type":"Image","props":{"y":377,"x":44,"width":662,"skin":"gameimg/bg2.png","height":200,"presetID":5,"sizeGrid":"20,20,20,20"},"compId":13,"child":[{"type":"Label","props":{"y":34,"x":31,"width":609,"text":"我的地址：","styleSkin":"comp/label.png","height":42,"fontSize":36,"font":"Microsoft YaHei","color":"#e59d61","align":"left","presetID":6},"compId":14},{"type":"Label","props":{"y":108,"x":30,"wordWrap":true,"width":609,"var":"address_txt","text":"-","styleSkin":"comp/label.png","height":46,"fontSize":28,"font":"Microsoft YaHei","color":"#f8e2d0","presetID":7},"compId":15}]},{"type":"Image","props":{"y":603,"x":44,"width":662,"skin":"gameimg/bg2.png","height":200,"presetID":8,"sizeGrid":"20,20,20,20"},"compId":16,"child":[{"type":"Label","props":{"y":34,"x":30,"width":609,"text":"钱包：","styleSkin":"comp/label.png","height":42,"fontSize":36,"font":"Microsoft YaHei","color":"#e59d61","align":"left","presetID":9},"compId":17},{"type":"Label","props":{"y":108,"x":30,"wordWrap":true,"width":609,"var":"tokenAmount_txt","text":"-","styleSkin":"comp/label.png","height":46,"fontSize":28,"font":"Microsoft YaHei","color":"#f8e2d0","presetID":10},"compId":18}]},{"type":"Image","props":{"y":825,"x":44,"width":662,"skin":"gameimg/bg2.png","height":432,"presetID":11,"sizeGrid":"20,20,20,20"},"compId":19,"child":[{"type":"Label","props":{"y":34,"x":31,"width":609,"text":"邀请连接：","styleSkin":"comp/label.png","height":42,"fontSize":36,"font":"Microsoft YaHei","color":"#e59d61","align":"left","presetID":12},"compId":20},{"type":"Label","props":{"y":108,"x":30,"wordWrap":true,"width":609,"var":"ref_txt","text":"-","styleSkin":"comp/label.png","height":46,"fontSize":28,"font":"Microsoft YaHei","color":"#f8e2d0","presetID":13},"compId":21},{"type":"Sprite","props":{"y":19,"x":490,"var":"btnCopyRef","texture":"gameimg/btnbg3.png","presetID":14,"sizeGrid":"20,30,20,30"},"compId":23},{"type":"Label","props":{"y":31,"x":510,"wordWrap":true,"width":115,"text":"复制","styleSkin":"comp/label.png","height":30,"fontSize":28,"font":"Microsoft YaHei","color":"#f8e2d0","align":"center","presetID":15},"compId":24},{"type":"Image","props":{"y":201,"x":231,"width":200,"skin":"gameimg/bg4.png","height":200,"presetID":16,"sizeGrid":"10,10,10,10"},"compId":25}]}],"loadList":["gameimg/bg2.png","comp/label.png","gameimg/btnbg3.png","gameimg/bg4.png"],"loadList3D":[]}